[
    {
        "name": "Groceries",
        "items": [
            {
                "name": "Carrots",
                "items": [
                    {
                        "name": "Carrots (Loose)"
                    },
                    {
                        "name": "Carrots (bagged)"
                    }
                ]
            },
            {
                "name": "Bananas"
            }
        ]
    },
    {
        "name": "Electronics",
        "items": [
            {
                "name": "TVs"
            },
            {
                "name": "Mobile Phones"
            }
        ]
    }
]